{"nodes": [{"id": "methodology_brief", "label": "Methodology Brief (academic, ~7600 words)", "file_type": "paper", "source_file": "notes/05_methodology_brief.md", "source_location": null, "source_url": null, "captured_at": null, "author": "BUS410 Team 7", "contributor": null}, {"id": "methodology_brief_two_layer_arch", "label": "Two-Layer Architecture (diagnostic vs influenceable)", "file_type": "rationale", "source_file": "notes/05_methodology_brief.md", "source_location": null, "source_url": null, "captured_at": null, "author": "BUS410 Team 7", "contributor": null}, {"id": "methodology_brief_horizon_switch", "label": "Horizon switch from h+1 to h+3/h+6 (federal data lag)", "file_type": "rationale", "source_file": "notes/05_methodology_brief.md", "source_location": null, "source_url": null, "captured_at": null, "author": "BUS410 Team 7", "contributor": null}, {"id": "methodology_brief_residualization", "label": "Residualization fix (regress against n_cra_lenders cohort)", "file_type": "rationale", "source_file": "notes/05_methodology_brief.md", "source_location": null, "source_url": null, "captured_at": null, "author": "BUS410 Team 7", "contributor": null}, {"id": "methodology_brief_ablation_surprise", "label": "Ablation surprise at h+3 (intervention levers gain \u0394AP)", "file_type": "rationale", "source_file": "notes/05_methodology_brief.md", "source_location": null, "source_url": null, "captured_at": null, "author": "BUS410 Team 7", "contributor": null}, {"id": "methodology_brief_regime_split_h3_h6", "label": "Pre/post-COVID regime split at h+3 and h+6", "file_type": "rationale", "source_file": "notes/05_methodology_brief.md", "source_location": null, "source_url": null, "captured_at": null, "author": "BUS410 Team 7", "contributor": null}, {"id": "methodology_brief_xgboost_config", "label": "XGBoost frozen hyperparameters", "file_type": "rationale", "source_file": "notes/05_methodology_brief.md", "source_location": null, "source_url": null, "captured_at": null, "author": "BUS410 Team 7", "contributor": null}, {"id": "methodology_brief_target_definition", "label": "target_becomes_service_desert_h1 (bottom decile of n_cra_lenders within year x peer_group)", "file_type": "rationale", "source_file": "notes/05_methodology_brief.md", "source_location": null, "source_url": null, "captured_at": null, "author": "BUS410 Team 7", "contributor": null}, {"id": "methodology_brief_branch_dominance_h6", "label": "Branch-access 73% dominance at h+6 post-COVID", "file_type": "rationale", "source_file": "notes/05_methodology_brief.md", "source_location": null, "source_url": null, "captured_at": null, "author": "BUS410 Team 7", "contributor": null}, {"id": "methodology_brief_nguyen_citation", "label": "Nguyen 2017 'Out of Sight, Out of Mind' FRB FEDS paper", "file_type": "paper", "source_file": "notes/05_methodology_brief.md", "source_location": null, "source_url": "https://www.federalreserve.gov/econres/feds/out-of-sight-out-of-mind-nearby-branch-closures-and-small-business-growth.htm", "captured_at": null, "author": "Nguyen, H. Q.", "contributor": null}, {"id": "methodology_brief_cra_2023_rule_citation", "label": "FFIEC CRA Final Rule (October 2023)", "file_type": "paper", "source_file": "notes/05_methodology_brief.md", "source_location": null, "source_url": null, "captured_at": null, "author": "Federal Financial Institutions Examination Council", "contributor": null}], "edges": [{"source": "methodology_brief", "target": "methodology_brief_two_layer_arch", "relation": "references", "confidence": "EXTRACTED", "confidence_score": 1.0, "source_file": "notes/05_methodology_brief.md", "source_location": null, "weight": 1.0}, {"source": "methodology_brief", "target": "methodology_brief_horizon_switch", "relation": "references", "confidence": "EXTRACTED", "confidence_score": 1.0, "source_file": "notes/05_methodology_brief.md", "source_location": null, "weight": 1.0}, {"source": "methodology_brief", "target": "methodology_brief_residualization", "relation": "references", "confidence": "EXTRACTED", "confidence_score": 1.0, "source_file": "notes/05_methodology_brief.md", "source_location": null, "weight": 1.0}, {"source": "methodology_brief", "target": "methodology_brief_ablation_surprise", "relation": "references", "confidence": "EXTRACTED", "confidence_score": 1.0, "source_file": "notes/05_methodology_brief.md", "source_location": null, "weight": 1.0}, {"source": "methodology_brief", "target": "methodology_brief_regime_split_h3_h6", "relation": "references", "confidence": "EXTRACTED", "confidence_score": 1.0, "source_file": "notes/05_methodology_brief.md", "source_location": null, "weight": 1.0}, {"source": "methodology_brief", "target": "methodology_brief_xgboost_config", "relation": "references", "confidence": "EXTRACTED", "confidence_score": 1.0, "source_file": "notes/05_methodology_brief.md", "source_location": null, "weight": 1.0}, {"source": "methodology_brief", "target": "methodology_brief_target_definition", "relation": "references", "confidence": "EXTRACTED", "confidence_score": 1.0, "source_file": "notes/05_methodology_brief.md", "source_location": null, "weight": 1.0}, {"source": "methodology_brief", "target": "methodology_brief_branch_dominance_h6", "relation": "references", "confidence": "EXTRACTED", "confidence_score": 1.0, "source_file": "notes/05_methodology_brief.md", "source_location": null, "weight": 1.0}, {"source": "methodology_brief", "target": "methodology_brief_nguyen_citation", "relation": "cites", "confidence": "EXTRACTED", "confidence_score": 1.0, "source_file": "notes/05_methodology_brief.md", "source_location": null, "weight": 1.0}, {"source": "methodology_brief", "target": "methodology_brief_cra_2023_rule_citation", "relation": "cites", "confidence": "EXTRACTED", "confidence_score": 1.0, "source_file": "notes/05_methodology_brief.md", "source_location": null, "weight": 1.0}, {"source": "methodology_brief_two_layer_arch", "target": "readme_diagnostic_model", "relation": "conceptually_related_to", "confidence": "EXTRACTED", "confidence_score": 1.0, "source_file": "notes/05_methodology_brief.md", "source_location": null, "weight": 1.0}, {"source": "methodology_brief_two_layer_arch", "target": "readme_influenceable_model", "relation": "conceptually_related_to", "confidence": "EXTRACTED", "confidence_score": 1.0, "source_file": "notes/05_methodology_brief.md", "source_location": null, "weight": 1.0}, {"source": "methodology_brief_horizon_switch", "target": "readme_horizons_h3_h6", "relation": "conceptually_related_to", "confidence": "EXTRACTED", "confidence_score": 1.0, "source_file": "notes/05_methodology_brief.md", "source_location": null, "weight": 1.0}, {"source": "methodology_brief_residualization", "target": "design_brief_target_leakage", "relation": "conceptually_related_to", "confidence": "EXTRACTED", "confidence_score": 1.0, "source_file": "notes/05_methodology_brief.md", "source_location": null, "weight": 1.0}, {"source": "methodology_brief_target_definition", "target": "decision_rule_ap_threshold", "relation": "conceptually_related_to", "confidence": "EXTRACTED", "confidence_score": 1.0, "source_file": "notes/05_methodology_brief.md", "source_location": null, "weight": 1.0}], "hyperedges": []}